take_easy/__init__.py
take_easy/cli.py
take_easy/converter/__init__.py
take_easy/converter/parquet_and_csv.py
take_easy_for_dataset-0.1.dev2.dist-info/METADATA
take_easy_for_dataset-0.1.dev2.dist-info/WHEEL
take_easy_for_dataset-0.1.dev2.dist-info/entry_points.txt
take_easy_for_dataset-0.1.dev2.dist-info/top_level.txt
take_easy_for_dataset-0.1.dev2.dist-info/RECORD
